rayflare/__init__.py
rayflare/angles.py
rayflare/options.py
rayflare/structure.py
rayflare/utilities.py
rayflare/analytic/__init__.py
rayflare/analytic/diffraction.py
rayflare/matrix_formalism/__init__.py
rayflare/matrix_formalism/ideal_cases.py
rayflare/matrix_formalism/multiply_matrices.py
rayflare/matrix_formalism/process_structure.py
rayflare/ray_tracing/__init__.py
rayflare/ray_tracing/analytical_rt.py
rayflare/ray_tracing/rt_common.py
rayflare/ray_tracing/rt_matrix.py
rayflare/ray_tracing/rt_structure.py
rayflare/rigorous_coupled_wave_analysis/__init__.py
rayflare/rigorous_coupled_wave_analysis/rcwa.py
rayflare/textures/__init__.py
rayflare/textures/define_textures.py
rayflare/textures/standard_rt_textures.py
rayflare/transfer_matrix_method/__init__.py
rayflare/transfer_matrix_method/lookup_table.py
rayflare/transfer_matrix_method/tmm.py
rayflare-2.0.1.dist-info/METADATA
rayflare-2.0.1.dist-info/WHEEL
rayflare-2.0.1.dist-info/licenses/LICENSE.txt
rayflare-2.0.1.dist-info/RECORD
