Metadata-Version: 2.3
Name: rayflare
Version: 2.0.1
Summary: Python-based integrated optical modelling
Project-URL: Homepage, https://github.com/qpv-research-group/rayflare
Project-URL: Documentation, https://rayflare.readthedocs.io
Project-URL: Changelog, https://rayflare.readthedocs.io/en/latest/news.html
Author-email: Phoebe Pearce <p.m.pearce@gmail.com>
License: RayFlare is a programme for flexible modelling of complicated optical structures.
License-File: LICENSE.txt
Keywords:  ray optics,diffraction,ellipsometry,lens,lens design,lens simulation,light scattering,light trapping,optics,photovoltaics,physics,ray tracing,rcwa,rigorous coupled wave analysis,scattering,thin film,thin film optics,tmm,transfer matrix,wave optics
Classifier: Development Status :: 5 - Production/Stable
Classifier: Intended Audience :: Science/Research
Classifier: License :: OSI Approved
Classifier: License :: OSI Approved :: GNU General Public License v3 (GPLv3)
Classifier: Natural Language :: English
Classifier: Operating System :: OS Independent
Classifier: Programming Language :: Python
Classifier: Programming Language :: Python :: 3
Classifier: Topic :: Scientific/Engineering
Classifier: Topic :: Scientific/Engineering :: Physics
Requires-Python: >=3.9
Requires-Dist: inkstone
Requires-Dist: joblib
Requires-Dist: matplotlib
Requires-Dist: numba
Requires-Dist: numpy<2.0.0
Requires-Dist: scipy
Requires-Dist: seaborn
Requires-Dist: solcore
Requires-Dist: sparse
Requires-Dist: xarray>=v2024.07.0
